{"preventUpnDetectSso":false,"silentUpdateTriggered":false,"featureLaunchInfo":{"enableUpnSilentSignin":-1},"previousCrashesInfo":{"crashes":[{"datetime":1613987707926,"type":"renderer","isPreviousCrash":true},{"datetime":1603990304050,"type":"renderer","isPreviousCrash":true},{"datetime":1603990295747,"type":"renderer","isPreviousCrash":true}]},"windowState":{"monitorId":21442559853606464,"x":0,"y":0,"width":1920,"height":1056,"isMaximized":false,"isFullScreen":false},"surfaceHubWindowState":{"monitorId":-1,"x":0,"y":0,"width":400,"height":600,"isMaximized":true,"isFullScreen":false},"restartCommand":{},"upnWindowUserUpn":"Oswaldo.Nickel@pfennigparade.de","userUpn":"","userOid":"63230950-281e-422d-8d56-954020c7b7b1","userTid":"fa6091e2-d174-42cc-bb94-892e54872398","guestTenantId":"fa6091e2-d174-42cc-bb94-892e54872398","homeTenantId":"","webAccountId":"","webAccountProviderType":"","launchTime":"1617638235168","desktopZoomLevelV2":5,"guestTenantIds":{},"userAccounts":{},"signedInActiveUser":{},"tidOidMap":{},"isAppFirstRun":false,"upnScreenShowCount":0,"desktopSessionId":"desktop-6142e852-4de2-4520-83a4-f86bfd634866","teamsUrlProtocolsRegistered":false,"lyncUrlProtocolsRegistered":false,"disableWarningOnOpenKeyRegistered":false,"previousElectronVersion":"8.5.3","lastKnownElectronVersion":"8.5.5","signInRestrictionsLicenseType":"","machineId":"4e7dd06bf069d0bf88198351b79f5d0a23663cc4f8a1d91fb949f8673196401d","deviceInfoId":"5c2d315edfec2220838bf3ecf51fd703df5c2f989ba318bd2f2963b45d22cea3","appPreferenceSettings":{"disableGpu":false,"openAtLogin":true,"openAsHidden":false,"runningOnClose":true,"registerAsIMProvider":false},"currentWebLanguage":"de","isRunningWamBefore":false,"isForeground":false,"previousWebClientVersion":"41/1.0.0.2021030227","isLoggedOut":false,"restartInfo":null,"notificationWindowOnClose":true,"rendererCrashInfo":null,"theme":"dark"}